[
	{ "title":"round 1", "order": 1, "type": "regular" },
	{ "title":"round 2", "order": 2, "type": "regular" },
	{ "title":"round 3", "order": 3, "type": "regular" },
	{ "title":"round 4", "order": 4, "type": "regular" },
	{ "title":"round 5", "order": 5, "type": "regular" },
	{ "title":"round 6", "order": 6, "type": "regular" },
	{ "title":"round 7", "order": 7, "type": "regular" },
	{ "title":"round 8", "order": 8, "type": "regular" },
	{ "title":"round 9", "order": 9, "type": "regular" },
	{ "title":"round 10", "order": 10, "type": "regular" },
	{ "title":"round 11", "order": 11, "type": "regular" },
	{ "title":"state of origin 1", "order": 12, "type": "state of origin" },
	{ "title":"round 12", "order": 13, "type": "regular" },
	{ "title":"round 13", "order": 14, "type": "regular" },
	{ "title":"round 14", "order": 15, "type": "regular" },
	{ "title":"state of origin 2", "order": 16, "type": "state of origin" },
	{ "title":"round 15", "order": 17, "type": "regular" },
	{ "title":"round 16", "order": 18, "type": "regular" },
	{ "title":"round 17", "order": 19, "type": "regular" },
	{ "title":"state of origin 3", "order": 20, "type": "state of origin" },
	{ "title":"round 18", "order": 21, "type": "regular" },
	{ "title":"round 19", "order": 22, "type": "regular" },
	{ "title":"round 20", "order": 23, "type": "regular" },
	{ "title":"round 21", "order": 24, "type": "regular" },
	{ "title":"round 22", "order": 25, "type": "regular" },
	{ "title":"round 23", "order": 26, "type": "regular" },
	{ "title":"round 24", "order": 27, "type": "regular" },
	{ "title":"round 25", "order": 28, "type": "regular" },
	{ "title":"round 26", "order": 29, "type": "regular" },
	{ "title":"finals week one", "order": 30, "type": "final" },
	{ "title":"finals week two", "order": 31, "type": "final" },
	{ "title":"finals week three", "order": 32, "type": "final" },
	{ "title":"grand final", "order": 33, "type": "final" }
]